{
  "_fv": 73,
  "_type": "tool",
  "definition": {
    "toolType": "Pickaxe",
    "renderType": 0,
    "blockingRenderType": 0,
    "texture": "meteoric_pickaxe",
    "customModelName": "Normal",
    "blockingModelName": "Normal blocking",
    "name": "Meteoric Pickaxe",
    "specialInformation": {
      "fixedValue": []
    },
    "creativeTabs": [
      {
        "value": "CUSTOM:AncientForkway"
      }
    ],
    "efficiency": 11.0,
    "attackSpeed": 1.0,
    "enchantability": 20,
    "damageVsEntity": 9.0,
    "usageCount": 3192,
    "glowCondition": {
      "fixedValue": false
    },
    "repairItems": [
      {
        "value": "CUSTOM:MeteoricIngot"
      }
    ],
    "immuneToFire": true,
    "blockDropsTier": "NETHERITE",
    "blocksAffected": [],
    "stayInGridWhenCrafting": false,
    "damageOnCrafting": false
  }
}